[{"name":"Akpweh","lastName":"Ma\u00eblle","phone":"066543225","email":"maelle@mail.fr","birthday":"1997-12-23T00:00:00","postalCode":"33800","city":"Bordeaux","street":"7 rue de Labr\u00e8de","ordersC":null,"id":5},{"name":"Akpweh","lastName":"Ma\u00eblle2","phone":"066543225","email":"maelle2@mail.fr","birthday":"1997-12-23T00:00:00","postalCode":"33800","city":"Bordeaux","street":"7 rue de Labr\u00e8de","ordersC":null,"id":6},{"name":"Akpweh","lastName":"Ma\u00eblle3","phone":"066543225","email":"maelle3@mail.fr","birthday":"1997-12-23T00:00:00","postalCode":"33800","city":"Bordeaux","street":"7 rue de Labr\u00e8de","ordersC":null,"id":7},{"name":"Akpweh","lastName":"Ma\u00eblle4","phone":"066543225","email":"maelle4@mail.fr","birthday":"1997-12-23T00:00:00","postalCode":"33800","city":"Bordeaux","street":"7 rue de Labr\u00e8de","ordersC":null,"id":8},{"name":"Akpweh","lastName":"Ma\u00eblle5","phone":"066543225","email":"maelle5@mail.fr","birthday":"1997-12-23T00:00:00","postalCode":"33800","city":"Bordeaux","street":"7 rue de Labr\u00e8de","ordersC":null,"id":9},{"name":"Akpweh","lastName":"Ma\u00eblle6","phone":"066543225","email":"maelle6@mail.fr","birthday":"1997-12-23T00:00:00","postalCode":"33800","city":"Bordeaux","street":"7 rue de Labr\u00e8de","ordersC":null,"id":10},{"name":"Akpweh","lastName":"Ma\u00eblle7","phone":"066543225","email":"maelle7@mail.fr","birthday":"1997-12-23T00:00:00","postalCode":"33800","city":"Bordeaux","street":"7 rue de Labr\u00e8de","ordersC":null,"id":11},{"name":"Akpweh","lastName":"Ma\u00eblle8","phone":"066543225","email":"maelle8@mail.fr","birthday":"1997-12-23T00:00:00","postalCode":"33800","city":"Bordeaux","street":"7 rue de Labr\u00e8de","ordersC":null,"id":12},{"name":"Akpweh","lastName":"Ma\u00eblle9","phone":"066543225","email":"maelle9@mail.fr","birthday":"1997-12-23T00:00:00","postalCode":"33800","city":"Bordeaux","street":"7 rue de Labr\u00e8de","ordersC":null,"id":13},{"name":"Akpweh","lastName":"Ma\u00eblle10","phone":"066543225","email":"maelle10@mail.fr","birthday":"1997-12-23T00:00:00","postalCode":"33800","city":"Bordeaux","street":"7 rue de Labr\u00e8de","ordersC":null,"id":14},{"id":986680830,"name":"Ardouin","lastName":"L&eacute;opold","phone":"0606060606","email":"leoplod@mail.fr","birthday":"2023-02-02","postalCode":"33800","city":"Bordeaux","street":"rue "},{"id":1942239513,"name":"dconj","lastName":"jnjd","phone":"jnjnc","email":"nicd","birthday":"2023-12-20","postalCode":"niuj","city":"niuczh","street":"njduns"},{"id":1957568080,"name":"b,jgh","lastName":"vchnjf","phone":"vcnh","email":"bcng","birthday":"2023-01-21","postalCode":"ghg","city":"gfg","street":"dht"},{"name":"rfh","lastName":"gjh","phone":"fhy","email":"fh","birthday":"2023-01-21","postalCode":"gyjut","city":"gfhj","street":"cg"}]